capella_console_client/__init__.py
capella_console_client/assets.py
capella_console_client/cli/__init__.py
capella_console_client/cli/cache.py
capella_console_client/cli/checkout.py
capella_console_client/cli/client_singleton.py
capella_console_client/cli/config.py
capella_console_client/cli/info.py
capella_console_client/cli/orders.py
capella_console_client/cli/prompt_helpers.py
capella_console_client/cli/sanitize.py
capella_console_client/cli/search.py
capella_console_client/cli/settings.py
capella_console_client/cli/user_searches/__init__.py
capella_console_client/cli/user_searches/core.py
capella_console_client/cli/user_searches/my_search_queries.py
capella_console_client/cli/user_searches/my_search_results.py
capella_console_client/cli/user_searches/my_searches.py
capella_console_client/cli/validate.py
capella_console_client/cli/visualize.py
capella_console_client/cli/wizard.py
capella_console_client/cli/workflows.py
capella_console_client/client.py
capella_console_client/config.py
capella_console_client/deprecation.py
capella_console_client/enumerations.py
capella_console_client/exceptions.py
capella_console_client/hooks.py
capella_console_client/logconf.py
capella_console_client/order.py
capella_console_client/py.typed
capella_console_client/repeat_request.py
capella_console_client/s3.py
capella_console_client/search.py
capella_console_client/session.py
capella_console_client/sort.py
capella_console_client/tasking_request.py
capella_console_client/validate.py
capella_console_client/version.py
capella_console_client-0.16.1.dist-info/LICENSE
capella_console_client-0.16.1.dist-info/METADATA
capella_console_client-0.16.1.dist-info/WHEEL
capella_console_client-0.16.1.dist-info/entry_points.txt
capella_console_client-0.16.1.dist-info/RECORD
