Metadata-Version: 2.3
Name: capella-console-client
Version: 0.16.1
Summary: Python SDK for api.capellaspace.com (task, search, order, download)
License: MIT
Keywords: Capella Space,Earth Observation,Capella Console,Synthetic Aperture Radar,SAR
Author: Thomas Beyer
Author-email: thomas.beyer@capellaspace.com
Requires-Python: >=3.9,<4.0
Classifier: Development Status :: 4 - Beta
Classifier: Intended Audience :: Developers
Classifier: License :: OSI Approved :: MIT License
Classifier: Programming Language :: Python
Classifier: Programming Language :: Python :: 3
Classifier: Programming Language :: Python :: 3.9
Classifier: Programming Language :: Python :: 3.10
Classifier: Programming Language :: Python :: 3.11
Classifier: Programming Language :: Python :: 3.12
Classifier: Programming Language :: Python :: 3.13
Classifier: Programming Language :: Python :: 3 :: Only
Classifier: Topic :: Scientific/Engineering :: Image Processing
Classifier: Topic :: Software Development :: Libraries
Provides-Extra: docs
Provides-Extra: s3
Provides-Extra: wizard
Requires-Dist: Sphinx (>=5.1.1,<6.0.0) ; extra == "docs"
Requires-Dist: botocore[s3] (>=1.36.11,<2.0.0) ; extra == "s3"
Requires-Dist: cloudpathlib[s3] (>=0.20.0,<0.21.0) ; extra == "s3"
Requires-Dist: geojson (>=3.0.1,<4.0.0)
Requires-Dist: httpx (>=0.27.0,<0.28.0)
Requires-Dist: keyring[wizard] (>=25.6.0,<26.0.0) ; extra == "wizard"
Requires-Dist: python-dateutil (>=2.8.2,<3.0.0)
Requires-Dist: questionary (>=1.10.0,<2.0.0) ; extra == "wizard"
Requires-Dist: retrying (>=1.3.3,<2.0.0)
Requires-Dist: rich (>=13.7.1,<14.0.0)
Requires-Dist: setuptools (>=69.0.2,<=78.1.1)
Requires-Dist: sphinx-autobuild (>=2021.3.14,<2022.0.0) ; extra == "docs"
Requires-Dist: sphinx-autodoc-typehints (>=1.19.2,<2.0.0) ; extra == "docs"
Requires-Dist: sphinx-copybutton (>=0.5.0,<0.6.0) ; extra == "docs"
Requires-Dist: sphinx-rtd-theme (>=1.0.0,<2.0.0) ; extra == "docs"
Requires-Dist: tabulate (>=0.8.10,<0.9.0) ; extra == "wizard"
Requires-Dist: typer (>=0.6.1,<0.7.0) ; extra == "wizard"
Project-URL: Documentation, https://capella-console-client.readthedocs.io/
Project-URL: Repository, https://github.com/capellaspace/console-client
